README.md
setup.cfg
setup.py
propnet/__init__.py
propnet/cli.py
propnet.egg-info/PKG-INFO
propnet.egg-info/SOURCES.txt
propnet.egg-info/dependency_links.txt
propnet.egg-info/entry_points.txt
propnet.egg-info/requires.txt
propnet.egg-info/top_level.txt