Metadata-Version: 1.1
Name: propnet
Version: 2019.9.25
Summary: A knowledge graph for Materials Science. Not yet ready for public use.
Home-page: https://github.com/materialsintelligence/propnet
Author: Propnet Development Team
Author-email: mkhorton@lbl.gov
License: UNKNOWN
Download-URL: https://github.com/materialsintelligence/propnet/archive/0.0.tar.gz
Platform: UNKNOWN
